exp_6_DLP_design/src/serial_pe/serial_pe.v
module serial_pe(
  input                clk,
  input                rst_n,
  input  signed [15:0] neuron,
  input  signed [15:0] weight,
  input         [ 1:0] ctl,
  input                vld_i,
  output        [31:0] result,
  output reg           vld_o
);

/*乘法器*/  /*TODO*/
wire signed [31:0] mult_res = neuron * weight;
reg [31:0] psum_r;

/*加法器*/  /*TODO*/
wire [31:0] psum_d = psum_r + mult_res;

/*部分和寄存器*/
always@(posedge clk or negedge rst_n)
if(!rst_n) begin
  psum_r <= 32'h0;
end else if(vld_i) begin
  psum_r <= psum_d;
end

always@(posedge clk or negedge rst_n)
if(!rst_n) begin
  vld_o <= 1'b0;
end else if(ctl[1]) begin
  vld_o <= 1'b1;
end else begin
  vld_o <= 1'b0;
end

assign result = psum_r;

endmodule

exp_6_DLP_design/src/serial_pe/tb_top_0.v
`timescale 1ns/1ps

module tb_top;
localparam WIDTH = 32;

reg        clk; // clk
reg        rst_n; // reset

initial begin
    clk = 1'b0;
    forever #0.5 clk = ~clk;
end
initial begin
    rst_n = 1'b0;
    #10 rst_n = 1'b1;
end
initial begin
  $dumpfile("tb_top_0.vcd");
  $dumpvars(0, tb_top);
end
initial begin
    #10000;
    $finish;
end

reg [7  :0] inst[3:0];
reg [511:0] neuron[139:0];
reg [511:0] weight[139:0];
reg [ 44:0] result[3:0];

initial
begin
  $readmemh("/Users/yulong/Documents/intelligent-computing-systems-library/exp_6_DLP_design/data/inst", inst);
  $readmemh("/Users/yulong/Documents/intelligent-computing-systems-library/exp_6_DLP_design/data/neuron", neuron);
  $readmemh("/Users/yulong/Documents/intelligent-computing-systems-library/exp_6_DLP_design/data/weight", weight);
  $readmemb("/Users/yulong/Documents/intelligent-computing-systems-library/exp_6_DLP_design/data/result", result);
end

reg [ 1:0]   inst_addr;
reg [12:0]   iter;
reg [15:0]   neuron_addr;
reg [15:0]   weight_addr;

wire [  7:0] pe_inst        = inst[inst_addr];
wire [511:0] pe_weight_line = weight[weight_addr[15:5]];
wire [511:0] pe_neuron_line = neuron[neuron_addr[15:5]];
wire [ 15:0] pe_weight      = pe_weight_line[(16*(31-weight_addr[4:0]))+:16];
wire [ 15:0] pe_neuron      = pe_neuron_line[(16*(31-neuron_addr[4:0]))+:16];
wire [1:0] pe_ctl;
assign pe_ctl[0] = (iter[12:0] == 13'h0);
assign pe_ctl[1] = (iter[12:5] == (pe_inst[7:0] - 1'b1)) && (iter[4:0] == 5'h1f);

reg pe_vld_i;
always@(posedge clk or negedge rst_n) begin
  if(!rst_n) begin
    pe_vld_i <= 1'b0;
  end else if((inst_addr == 2'h0) && (neuron_addr == 16'h0) && (weight_addr == 16'h0)) begin
    pe_vld_i <= 1'b1;
  end else if(pe_ctl[1] && pe_vld_i && (inst_addr != 2'h3)) begin
    pe_vld_i <= 1'b0;
  end else begin
    pe_vld_i <= 1'b1;
  end
end

always@(posedge clk or negedge rst_n) begin
  if(!rst_n) begin
    iter <= 13'b0;
  end else if(pe_ctl[1] && pe_vld_i && (inst_addr != 2'h3)) begin
    iter <= 13'b0;
  end else if(pe_vld_i) begin
    iter <= iter + 1'b1;
  end
end

always@(posedge clk or negedge rst_n) begin
  if(!rst_n) begin
    inst_addr <= 2'b0;
  end else if(pe_ctl[1] && pe_vld_i && (inst_addr != 2'h3)) begin
    inst_addr <= inst_addr + 1'b1;
  end
end

always@(posedge clk or negedge rst_n) begin
  if(!rst_n) begin
    weight_addr <= 16'h0;
  end else if(pe_vld_i) begin
    weight_addr <= weight_addr + 1'b1;
  end
end

always@(posedge clk or negedge rst_n) begin
  if(!rst_n) begin
    neuron_addr <= 16'h0;
  end else if(pe_vld_i) begin
    neuron_addr <= neuron_addr + 1'b1;
  end
end

wire [31:0] pe_result;
wire pe_vld_o;
serial_pe u_serial_pe (
  .clk                  (clk      ),
  .rst_n                (rst_n    ),
  .neuron               (pe_neuron),
  .weight               (pe_weight),
  .ctl                  (pe_ctl   ),
  .vld_i                (pe_vld_i ),
  .result               (pe_result),
  .vld_o                (pe_vld_o )
);

reg [1:0] result_addr;
reg compare_pass;
always@(posedge clk or negedge rst_n) begin
  if(!rst_n) begin
    result_addr <= 2'h0;
  end else if(pe_vld_o) begin
    result_addr <= result_addr + 1'b1;
  end
end

always@(posedge clk or negedge rst_n) begin
 if(!rst_n) begin
   compare_pass <= 1'b1;
 end else if(pe_vld_o && (pe_result != result[result_addr][31:0])) begin
   $display("FAIL:\n num.%d result not correct!!!\npe_result is %x,result is %x\n", result_addr,pe_result,result[result_addr][31:0]);
  //  $display("FAIL: num.%d result not correct!!!", result_addr);
   compare_pass <= 1'b0;
 end else if(pe_vld_o && (pe_result == result[result_addr][31:0])) begin
   $display("INFO: num.%d result is correct.", result_addr);
 end
end

endmodule

exp_6_DLP_design/src/serial_pe/tb_top_0.vcd
$date
	Sun Apr 23 23:03:53 2023
$end
$version
	Icarus Verilog
$end
$timescale
	1ps
$end
$scope module tb_top $end
$var wire 8 ! pe_inst [7:0] $end
$var wire 512 " pe_neuron_line [511:0] $end
$var wire 512 # pe_weight_line [511:0] $end
$var wire 16 $ pe_weight [15:0] $end
$var wire 1 % pe_vld_o $end
$var wire 32 & pe_result [31:0] $end
$var wire 16 ' pe_neuron [15:0] $end
$var wire 2 ( pe_ctl [1:0] $end
$var reg 1 ) clk $end
$var reg 1 * compare_pass $end
$var reg 2 + inst_addr [1:0] $end
$var reg 13 , iter [12:0] $end
$var reg 16 - neuron_addr [15:0] $end
$var reg 1 . pe_vld_i $end
$var reg 2 / result_addr [1:0] $end
$var reg 1 0 rst_n $end
$var reg 16 1 weight_addr [15:0] $end
$scope module u_serial_pe $end
$var wire 1 ) clk $end
$var wire 2 2 ctl [1:0] $end
$var wire 16 3 neuron [15:0] $end
$var wire 32 4 result [31:0] $end
$var wire 1 0 rst_n $end
$var wire 1 . vld_i $end
$var wire 16 5 weight [15:0] $end
$var wire 32 6 psum_d [31:0] $end
$var wire 32 7 mult_res [31:0] $end
$var reg 32 8 psum_r [31:0] $end
$var reg 1 % vld_o $end
$upscope $end
$upscope $end
$enddefinitions $end
#0
$dumpvars
b0 8
bx 7
bx 6
bx 5
b0 4
bx 3
bx 2
bx 1
00
bx /
x.
bx -
bx ,
bx +
x*
0)
bx (
bx '
b0 &
0%
bx $
bx #
bx "
bx !
$end
#500
b11110110010011110101100011011000 6
b11110110010011110101100011011000 7
b100100000101000 $
b100100000101000 5
b1001000001010000110100111001000101000001011010111100010100010101111000101011110001001111000011001001000000100010101011000111010111000110100100100001110101110101101000101100110010011011011101110101000110000110011111011101011000111100110000111001100101101001110010000110011010011010100001101011100101110011101100011100011110111011111010100100001101101111100011101111000101011001011111111000101001100111101011101111010111001101011011010010001010011000000000000011010000001001110011110100101101111001011101110100011 #
b1101110110011111 '
b1101110110011111 3
b11011101100111111101010110110001000110010000010111110111100010000010101110011001011000000100101110000010111100100100001101001110010000101101011001011000110110010001100000001100100111001101101100000110010010000111001011001011001111101111001101010001001101011110010100010000110000000011011110101111111000010000010000001011001111100100101111100000011101001011110010001101101101101100111001100010001001001110011100001010010100111011101110010111000111000000011010101010111000010010110011100100010111001110001101100100 "
0.
b1 (
b1 2
b0 ,
b10100 !
b0 +
b0 1
b0 -
b0 /
1*
1)
#1000
0)
#1500
1)
#2000
0)
#2500
1)
#3000
0)
#3500
1)
#4000
0)
#4500
1)
#5000
0)
#5500
1)
#6000
0)
#6500
1)
#7000
0)
#7500
1)
#8000
0)
#8500
1)
#9000
0)
#9500
1)
#10000
0)
10
#10500
1.
1)
#11000
0)
#11500
b1101010110110001 '
b1101010110110001 3
b11101110100001001000101101001000 7
b110100111001000 $
b110100111001000 5
b11100100110100111110010000100000 6
b11110110010011110101100011011000 &
b11110110010011110101100011011000 4
b11110110010011110101100011011000 8
b1 -
b1 1
b0 (
b0 2
b1 ,
1)
#12000
0)
#12500
b1010000010110101 $
b1010000010110101 5
b11110110101011111101000010001001 7
b1100100000101 '
b1100100000101 3
b10 ,
b10 1
b10 -
b11011011100000111011010010101001 6
b11100100110100111110010000100000 &
b11100100110100111110010000100000 4
b11100100110100111110010000100000 8
1)
#13000
0)
#13500
b1111011110001000 '
b1111011110001000 3
b111110010111111101010000 7
b1110001010001010 $
b1110001010001010 5
b11011100011111010011001111111001 6
b11011011100000111011010010101001 &
b11011011100000111011010010101001 4
b11011011100000111011010010101001 8
b11 -
b11 1
b11 ,
1)
#14000
0)
#14500
b1111000101011110 $
b1111000101011110 5
b11111101100000100000101100101110 7
b10101110011001 '
b10101110011001 3
b100 ,
b100 1
b100 -
b11011001111111110011111100100111 6
b11011100011111010011001111111001 &
b11011100011111010011001111111001 4
b11011100011111010011001111111001 8
1)
#15000
0)
#15500
b110000001001011 '
b110000001001011 3
b1110110111011101010001000010 7
b10011110000110 $
b10011110000110 5
b11101000110111010001001101101001 6
b11011001111111110011111100100111 &
b11011001111111110011111100100111 4
b11011001111111110011111100100111 8
b101 -
b101 1
b101 ,
1)
#16000
0)
#16500
b100100000010001 $
b100100000010001 5
b11011100110010111100001000010010 7
b1000001011110010 '
b1000001011110010 3
b110 ,
b110 1
b110 -
b11000101101010001101010101111011 6
b11101000110111010001001101101001 &
b11101000110111010001001101101001 4
b11101000110111010001001101101001 8
1)
#17000
0)
#17500
b100001101001110 '
b100001101001110 3
b10110101010110111001110101100 7
b101011000111010 $
b101011000111010 5
b11011100010101000100100100100111 6
b11000101101010001101010101111011 &
b11000101101010001101010101111011 4
b11000101101010001101010101111011 8
b111 -
b111 1
b111 ,
1)
#18000
0)
#18500
b1110001101001001 $
b1110001101001001 5
b11111000100000001101000100000110 7
b100001011010110 '
b100001011010110 3
b1000 ,
b1000 1
b1000 -
b11010100110101010001101000101101 6
b11011100010101000100100100100111 &
b11011100010101000100100100100111 4
b11011100010101000100100100100111 8
1)
#19000
0)
#19500
b101100011011001 '
b101100011011001 3
b101000111000110101110101010 7
b111010111010 $
b111010111010 5
b11011001111100011000010111010111 6
b11010100110101010001101000101101 &
b11010100110101010001101000101101 4
b11010100110101010001101000101101 8
b1001 -
b1001 1
b1001 ,
1)
#20000
0)
#20500
b1101000101100110 $
b1101000101100110 5
b11111011100111110110000011001000 7
b1100000001100 '
b1100000001100 3
b1010 ,
b1010 1
b1010 -
b11010101100100001110011010011111 6
b11011001111100011000010111010111 &
b11011001111100011000010111010111 4
b11011001111100011000010111010111 8
1)
#21000
0)
#21500
b1001110011011011 '
b1001110011011011 3
b11100001111001010111001011111001 7
b100110110111011 $
b100110110111011 5
b10110111011101100101100110011000 6
b11010101100100001110011010011111 &
b11010101100100001110011010011111 4
b11010101100100001110011010011111 8
b1011 -
b1011 1
b1011 ,
1)
#22000
0)
#22500
b1010100011000011 $
b1010100011000011 5
b11111101110111000000100011011000 7
b11001001000 '
b11001001000 3
b1100 ,
b1100 1
b1100 -
b10110101010100100110001001110000 6
b10110111011101100101100110011000 &
b10110111011101100101100110011000 4
b10110111011101100101100110011000 8
1)
#23000
0)
#23500
b111001011001011 '
b111001011001011 3
b11100001101101000101001011001 7
b11111011101011 $
b11111011101011 5
b11010001100010001110110011001001 6
b10110101010100100110001001110000 &
b10110101010100100110001001110000 4
b10110101010100100110001001110000 8
b1101 -
b1101 1
b1101 ,
1)
#24000
0)
#24500
b1111001100001 $
b1111001100001 5
b111011110000101010000010011 7
b11111011110011 '
b11111011110011 3
b1110 ,
b1110 1
b1110 -
b11011001000000010100000011011100 6
b11010001100010001110110011001001 &
b11010001100010001110110011001001 4
b11010001100010001110110011001001 8
1)
#25000
0)
#25500
b101000100110101 '
b101000100110101 3
b11101111101110100101010101000100 7
b1100110010110100 $
b1100110010110100 5
b11001000101110111001011000100000 6
b11011001000000010100000011011100 &
b11011001000000010100000011011100 4
b11011001000000010100000011011100 8
b1111 -
b1111 1
b1111 ,
1)
#26000
0)
#26500
b1110010000110011 $
b1110010000110011 5
b10111011001110001000110000 7
b1110010100010000 '
b1110010100010000 3
b10000 ,
b10000 1
b10000 -
b11001011101010000111100001010000 6
b11001000101110111001011000100000 &
b11001000101110111001011000100000 4
b11001000101110111001011000100000 8
1)
#27000
0)
#27500
b1100000000110111 '
b1100000000110111 3
b11101100101111111101100101100101 7
b100110101000011 $
b100110101000011 5
b10111000011010000101000110110101 6
b11001011101010000111100001010000 &
b11001011101010000111100001010000 4
b11001011101010000111100001010000 8
b10001 -
b10001 1
b10001 ,
1)
#28000
0)
#28500
b101110010111001 $
b101110010111001 5
b11100010111110101111010110011001 7
b1010111111100001 '
b1010111111100001 3
b10010 ,
b10010 1
b10010 -
b10011011011000110100011101001110 6
b10111000011010000101000110110101 &
b10111000011010000101000110110101 4
b10111000011010000101000110110101 8
1)
#29000
0)
#29500
b10000001011 '
b10000001011 3
b11111111011000011101110111000001 7
b1101100011100011 $
b1101100011100011 5
b10011010110001010010010100001111 6
b10011011011000110100011101001110 &
b10011011011000110100011101001110 4
b10011011011000110100011101001110 8
b10011 -
b10011 1
b10011 ,
1)
#30000
0)
#30500
b1101110111110101 $
b1101110111110101 5
b11110111101101110101110011000111 7
b11111001001011 '
b11111001001011 3
b10100 ,
b10100 1
b10100 -
b10010010011111001000000111010110 6
b10011010110001010010010100001111 &
b10011010110001010010010100001111 4
b10011010110001010010010100001111 8
1)
#31000
0)
#31500
b1110000001110100 '
b1110000001110100 3
b11111011110110000110011011101100 7
b10000110110111 $
b10000110110111 5
b10001110010101001110100011000010 6
b10010010011111001000000111010110 &
b10010010011111001000000111010110 4
b10010010011111001000000111010110 8
b10101 -
b10101 1
b10101 ,
1)
#32000
0)
#32500
b1100011101111000 $
b1100011101111000 5
b1110111001001111110100011000 7
b1011110010001101 '
b1011110010001101 3
b10110 ,
b10110 1
b10110 -
b10011101001110011110010111011010 6
b10001110010101001110100011000010 &
b10001110010101001110100011000010 4
b10001110010101001110100011000010 8
1)
#33000
0)
#33500
b1011011011001110 '
b1011011011001110 3
b10111110011011100101110110010 7
b1010110010111111 $
b1010110010111111 5
b10110101000001111011000110001100 6
b10011101001110011110010111011010 &
b10011101001110011110010111011010 4
b10011101001110011110010111011010 8
b10111 -
b10111 1
b10111 ,
1)
#34000
0)
#34500
b1100010100110011 $
b1100010100110011 5
b11101001011101010100000100101100 7
b110001000100100 '
b110001000100100 3
b11000 ,
b11000 1
b11000 -
b10011110011111001111001010111000 6
b10110101000001111011000110001100 &
b10110101000001111011000110001100 4
b10110101000001111011000110001100 8
1)
#35000
0)
#35500
b1110011100001010 '
b1110011100001010 3
b11111100111000000011000100 7
b1101011101111010 $
b1101011101111010 5
b10100010011100000111001101111100 6
b10011110011111001111001010111000 &
b10011110011111001111001010111000 4
b10011110011111001111001010111000 8
b11001 -
b11001 1
b11001 ,
1)
#36000
0)
#36500
b1110011010110110 $
b1110011010110110 5
b11110111101110101000100011110010 7
b101001110111011 '
b101001110111011 3
b11010 ,
b11010 1
b11010 -
b10011010001010101111110001101110 6
b10100010011100000111001101111100 &
b10100010011100000111001101111100 4
b10100010011100000111001101111100 8
1)
#37000
0)
#37500
b1001011100011100 '
b1001011100011100 3
b101101010110111011100001010000 7
b1001000101001100 $
b1001000101001100 5
b11000111100001101011010010111110 6
b10011010001010101111110001101110 &
b10011010001010101111110001101110 4
b10011010001010101111110001101110 8
b11011 -
b11011 1
b11011 ,
1)
#38000
0)
#38500
b11010 $
b11010 5
b1010110101000100 7
b11010101010 '
b11010101010 3
b11100 ,
b11100 1
b11100 -
b11000111100001110110001000000010 6
b11000111100001101011010010111110 &
b11000111100001101011010010111110 4
b11000111100001101011010010111110 8
1)
#39000
0)
#39500
b1110000100101100 '
b1110000100101100 3
b11111111011010001101111010110100 7
b10011100111 $
b10011100111 5
b11000110111100000100000010110110 6
b11000111100001110110001000000010 &
b11000111100001110110001000000010 4
b11000111100001110110001000000010 8
b11101 -
b11101 1
b11101 ,
1)
#40000
0)
#40500
b1010010110111100 $
b1010010110111100 5
b1001101111101111111110010000 7
b1110010001011100 '
b1110010001011100 3
b11110 ,
b11110 1
b11110 -
b11010000101011110100000001000110 6
b11000110111100000100000010110110 &
b11000110111100000100000010110110 4
b11000110111100000100000010110110 8
1)
#41000
0)
#41500
b1110001101100100 '
b1110001101100100 3
b111101000111101010010101100 7
b1011101110100011 $
b1011101110100011 5
b11011000010100110001010011110010 6
b11010000101011110100000001000110 &
b11010000101011110100000001000110 4
b11010000101011110100000001000110 8
b11111 -
b11111 1
b11111 ,
1)
#42000
0)
#42500
b1011011111000101100110110011100010000111101010001010111011101101011010001100011000111010101101101101111001110010111111011111000100010011001000011010110000111001000010000111011011011000100000101101100111010101010001101110011000101101001101100001101111101011001011110000011000001011110110110110111101010010001010001101010011100100101000010011110000010010001101110010011011001001101001000101111100101100100001110101100000000000011100010010101011010011001100111110110110110111000010000011101100111101111010101001110 #
b101101111100010 $
b101101111100010 5
b10010111000001010110000110101101100111011011101010110000111001011101110101111101111011101010000101100111010110110110100111010101111100110111110111000100011111111010101010110011000100100011100100000110110100101010101110000010101011110010010111101110001010110000001101001111110101111100000011001100100000111001010101101000101001100010011010100110011100001001000100010001001001001000000000111111111100110011110111100110110010100011100000101100110101101011010000111001110000001100000000100000010010100101000111110010 "
b11011010010100100001100101101010 7
b1001011100000101 '
b1001011100000101 3
b100000 ,
b100000 1
b100000 -
b10110010101001010010111001011100 6
b11011000010100110001010011110010 &
b11011000010100110001010011110010 4
b11011000010100110001010011110010 8
1)
#43000
0)
#43500
b110000110101101 '
b110000110101101 3
b11101100110001100000111001101100 7
b1100110110011100 $
b1100110110011100 5
b10011111011010110011110011001000 6
b10110010101001010010111001011100 &
b10110010101001010010111001011100 4
b10110010101001010010111001011100 8
b100001 -
b100001 1
b100001 ,
1)
#44000
0)
#44500
b100001111010100 $
b100001111010100 5
b11100101111101100100110000001000 7
b1001110110111010 '
b1001110110111010 3
b100010 ,
b100010 1
b100010 -
b10000101011000011000100011010000 6
b10011111011010110011110011001000 &
b10011111011010110011110011001000 4
b10011111011010110011110011001000 8
1)
#45000
0)
#45500
b1011000011100101 '
b1011000011100101 3
b11100100111110010101110010001110 7
b101011101110110 $
b101011101110110 5
b1101010010110101110010101011110 6
b10000101011000011000100011010000 &
b10000101011000011000100011010000 4
b10000101011000011000100011010000 8
b100011 -
b100011 1
b100011 ,
1)
#46000
0)
#46500
b1011010001100011 $
b1011010001100011 5
b1010001100011000101101010111 7
b1101110101111101 '
b1101110101111101 3
b100100 ,
b100100 1
b100100 -
b1110100100011000111000010110101 6
b1101010010110101110010101011110 &
b1101010010110101110010101011110 4
b1101010010110101110010101011110 8
1)
#47000
0)
#47500
b1110111010100001 '
b1110111010100001 3
b11111110000000100001000000111011 7
b1110101011011 $
b1110101011011 5
b1110010100011101000000011110000 6
b1110100100011000111000010110101 &
b1110100100011000111000010110101 4
b1110100100011000111000010110101 8
b100101 -
b100101 1
b100101 ,
1)
#48000
0)
#48500
b110111100111001 $
b110111100111001 5
b101100111001110111100001000011 7
b110011101011011 '
b110011101011011 3
b100110 ,
b100110 1
b100110 -
b10011111011101011111100100110011 6
b1110010100011101000000011110000 &
b1110010100011101000000011110000 4
b1110010100011101000000011110000 8
1)
#49000
0)
#49500
b110100111010101 '
b110100111010101 3
b110100011111010101110001011000 7
b111111011111000 $
b111111011111000 5
b11010011111100110101010110001011 6
b10011111011101011111100100110011 &
b10011111011101011111100100110011 4
b10011111011101011111100100110011 8
b100111 -
b100111 1
b100111 ,
1)
#50000
0)
#50500
b1000100110010000 $
b1000100110010000 5
b101110010011101101101010000 7
b1111001101111101 '
b1111001101111101 3
b101000 ,
b101000 1
b101000 -
b11011001101111010011000011011011 6
b11010011111100110101010110001011 &
b11010011111100110101010110001011 4
b11010011111100110101010110001011 8
1)
#51000
0)
#51500
b1100010001111111 '
b1100010001111111 3
b1001101111001010011111100100 7
b1101011000011100 $
b1101011000011100 5
b11100011011110011101100010111111 6
b11011001101111010011000011011011 &
b11011001101111010011000011011011 4
b11011001101111010011000011011011 8
b101001 -
b101001 1
b101001 ,
1)
#52000
0)
#52500
b1000010000111011 $
b1000010000111011 5
b101001001111011010001101000001 7
b1010101010110011 '
b1010101010110011 3
b101010 ,
b101010 1
b101010 -
b1100101101110111110000000000 6
b11100011011110011101100010111111 &
b11100011011110011101100010111111 4
b11100011011110011101100010111111 8
1)
#53000
0)
#53500
b1001000111001 '
b1001000111001 3
b111101101001010110001111001 7
b110110001000001 $
b110110001000001 5
b10100011011000010100001111001 6
b1100101101110111110000000000 &
b1100101101110111110000000000 4
b1100101101110111110000000000 8
b101011 -
b101011 1
b101011 ,
1)
#54000
0)
#54500
b110110011101010 $
b110110011101010 5
b10111001101101001111110100 7
b11011010010 '
b11011010010 3
b101100 ,
b101100 1
b101100 -
b10111010100101111110001101101 6
b10100011011000010100001111001 &
b10100011011000010100001111001 4
b10100011011000010100001111001 8
1)
#55000
0)
#55500
b1010101110000010 '
b1010101110000010 3
b11110100010111101000101100110 7
b1010001101110011 $
b1010001101110011 5
b110101110111101100110111010011 6
b10111010100101111110001101101 &
b10111010100101111110001101101 4
b10111010100101111110001101101 8
b101101 -
b101101 1
b101101 ,
1)
#56000
0)
#56500
b1011010011011 $
b1011010011011 5
b11111000110111000011100101100111 7
b1010111100100101 '
b1010111100100101 3
b101110 ,
b101110 1
b101110 -
b101110101110110000011100111010 6
b110101110111101100110111010011 &
b110101110111101100110111010011 4
b110101110111101100110111010011 8
1)
#57000
0)
#57500
b1110111000101011 '
b1110111000101011 3
b11111111000001110001111000100111 7
b110111110101 $
b110111110101 5
b101101110000100010010101100001 6
b101110101110110000011100111010 &
b101110101110110000011100111010 4
b101110101110110000011100111010 8
b101111 -
b101111 1
b101111 ,
1)
#58000
0)
#58500
b1001011110000011 $
b1001011110000011 5
b11111110101001100100101001101101 7
b1101001111 '
b1101001111 3
b110000 ,
b110000 1
b110000 -
b101100011010000110111111001110 6
b101101110000100010010101100001 &
b101101110000100010010101100001 4
b101101110000100010010101100001 8
1)
#59000
0)
#59500
b1101011111000000 '
b1101011111000000 3
b11111111000100010111110011000000 7
b10111101101 $
b10111101101 5
b101011011110011110110010001110 6
b101100011010000110111111001110 &
b101100011010000110111111001110 4
b101100011010000110111111001110 8
b110001 -
b110001 1
b110001 ,
1)
#60000
0)
#60500
b1011011110101001 $
b1011011110101001 5
b1110100011001010011101111011 7
b1100110010000011 '
b1100110010000011 3
b110010 ,
b110010 1
b110010 -
b111010000001101001010000001001 6
b101011011110011110110010001110 &
b101011011110011110110010001110 4
b101011011110011110110010001110 8
1)
#61000
0)
#61500
b1001010101101000 '
b1001010101101000 3
b11110111011111111111110100010000 7
b1010001101010 $
b1010001101010 5
b110001100001101001000100011001 6
b111010000001101001010000001001 &
b111010000001101001010000001001 4
b111010000001101001010000001001 8
b110011 -
b110011 1
b110011 ,
1)
#62000
0)
#62500
b111001001010000 $
b111001001010000 5
b11010111111000001101011111100000 7
b1010011000100110 '
b1010011000100110 3
b110100 ,
b110100 1
b110100 -
b1001011001110110100011111001 6
b110001100001101001000100011001 &
b110001100001101001000100011001 4
b110001100001101001000100011001 8
1)
#63000
0)
#63500
b1010011001110000 '
b1010011001110000 3
b100010010001011111100111110000 7
b1001111000001001 $
b1001111000001001 5
b101011101011010110001011101001 6
b1001011001110110100011111001 &
b1001011001110110100011111001 4
b1001011001110110100011111001 8
b110101 -
b110101 1
b110101 ,
1)
#64000
0)
#64500
b1101110010011 $
b1101110010011 5
b11110100000011010001011111000011 7
b1001000100010001 '
b1001000100010001 3
b110110 ,
b110110 1
b110110 -
b11111101110100111101010101100 6
b101011101011010110001011101001 &
b101011101011010110001011101001 4
b101011101011010110001011101001 8
1)
#65000
0)
#65500
b10010010000000 '
b10010010000000 3
b1110010111111111000100000000 7
b110010011010010 $
b110010011010010 5
b101110000110100110101110101100 6
b11111101110100111101010101100 &
b11111101110100111101010101100 4
b11111101110100111101010101100 8
b110111 -
b110111 1
b110111 ,
1)
#66000
0)
#66500
b10111110010110 $
b10111110010110 5
b1011111000110001010101100010 7
b11111111110011 '
b11111111110011 3
b111000 ,
b111000 1
b111000 -
b111001111111011000000100001110 6
b101110000110100110101110101100 &
b101110000110100110101110101100 4
b101110000110100110101110101100 8
1)
#67000
0)
#67500
b11110111100110 '
b11110111100110 3
b10000010111001100100010001000 7
b100001110101100 $
b100001110101100 5
b1001010010110100100100110010110 6
b111001111111011000000100001110 &
b111001111111011000000100001110 4
b111001111111011000000100001110 8
b111001 -
b111001 1
b111001 ,
1)
#68000
0)
#68500
b111000 $
b111000 5
b11111111111101000011110001000000 7
b1100101000111000 '
b1100101000111000 3
b111010 ,
b111010 1
b111010 -
b1001010010011101000010111010110 6
b1001010010110100100100110010110 &
b1001010010110100100100110010110 4
b1001010010110100100100110010110 8
1)
#69000
0)
#69500
b10110011010110 '
b10110011010110 3
b11101101010101001111000111000110 7
b1001010101101001 $
b1001010101101001 5
b110111101000110111011110011100 6
b1001010010011101000010111010110 &
b1001010010011101000010111010110 4
b1001010010011101000010111010110 8
b111011 -
b111011 1
b111011 ,
1)
#70000
0)
#70500
b1001100111110110 $
b1001100111110110 5
b11110001101000011111111000110 7
b1011010000111001 '
b1011010000111001 3
b111100 ,
b111100 1
b111100 -
b1010101110101111011011101100010 6
b110111101000110111011110011100 &
b110111101000110111011110011100 4
b110111101000110111011110011100 8
1)
#71000
0)
#71500
b1100000011000000 '
b1100000011000000 3
b1001000000111010001100000000 7
b1101101110000100 $
b1101101110000100 5
b1011110110110110101101001100010 6
b1010101110101111011011101100010 &
b1010101110101111011011101100010 4
b1010101110101111011011101100010 8
b111101 -
b111101 1
b111101 ,
1)
#72000
0)
#72500
b1110110011110 $
b1110110011110 5
b11101111000100111110101100 7
b10000001001010 '
b10000001001010 3
b111110 ,
b111110 1
b111110 -
b1100010100101111010101000001110 6
b1011110110110110101101001100010 &
b1011110110110110101101001100010 4
b1011110110110110101101001100010 8
1)
#73000
0)
#73500
b101000111110010 '
b101000111110010 3
b11111100100100111001000110111100 7
b1111010101001110 $
b1111010101001110 5
b1011111001010110011101111001010 6
b1100010100101111010101000001110 &
b1100010100101111010101000001110 4
b1100010100101111010101000001110 8
b111111 -
b111111 1
b111111 ,
1)
#74000
0)
#74500
b10000011111001011101111010001100100010110100100100101001111010010000101101101010110111111101110101110011000110000010000110101101011101100101101010111100010001100011010110001001111100101010001000111101001101000111100101110110101101100000101110010100000011100001010001010011101011010100101101111010001000100111110100101100101001010001011111010100011100111111111010111101100100011010111111011010000010000000010110110111111010010111111111000001010011000111101110111001001010000001011000000111100011110101001111101100 #
b1000001111100101 $
b1000001111100101 5
b110010101000000001001000101001001110011110000110001110111111100101101101100001010101111001001001110010110010011000101010100011011111010101100000100011111001100010111101110111010010011010000110001101000110111101110111101001110010000001011001111001110111101011000010110011001110011000110010100010010000000001001110000001001101001001011011001000011100110011000110000011100110011000010111101010110000001001000110010100011110110001011111110000110100110111100011010010000101001010100011001000011011101110110011001100 "
b11100111011101010010100100100000 7
b11001010100000 '
b11001010100000 3
b1000000 ,
b1000000 1
b1000000 -
b1000110101000000110010011101010 6
b1011111001010110011101111001010 &
b1011111001010110011101111001010 4
b1011111001010110011101111001010 8
1)
#75000
0)
#75500
b1001000101001 '
b1001000101001 3
b11111101101000000111110001101100 7
b1101111010001100 $
b1101111010001100 5
b1000100010000001110000101010110 6
b1000110101000000110010011101010 &
b1000110101000000110010011101010 4
b1000110101000000110010011101010 8
b1000001 -
b1000001 1
b1000001 ,
1)
#76000
0)
#76500
b1000101101001001 $
b1000101101001001 5
b11100101100111001010110000101001 7
b11100111100001 '
b11100111100001 3
b1000010 ,
b1000010 1
b1000010 -
b101001110111011000110101111111 6
b1000100010000001110000101010110 &
b1000100010000001110000101010110 4
b1000100010000001110000101010110 8
1)
#77000
0)
#77500
b1000111011111110 '
b1000111011111110 3
b11101101011111111101001100101110 7
b10100111101001 $
b10100111101001 5
b10111010111010110000010101101 6
b101001110111011000110101111111 &
b101001110111011000110101111111 4
b101001110111011000110101111111 8
b1000011 -
b1000011 1
b1000011 ,
1)
#78000
0)
#78500
b101101101010 $
b101101101010 5
b100000100110000000100101010 7
b101101101100001 '
b101101101100001 3
b1000100 ,
b1000100 1
b1000100 -
b11011011100000110000111010111 6
b10111010111010110000010101101 &
b10111010111010110000010101101 4
b10111010111010110000010101101 8
1)
#79000
0)
#79500
b101011110010010 '
b101011110010010 3
b11110101000000011100011100001010 7
b1101111111011101 $
b1101111111011101 5
b10000011100100010100011100001 6
b11011011100000110000111010111 &
b11011011100000110000111010111 4
b11011011100000110000111010111 8
b1000101 -
b1000101 1
b1000101 ,
1)
#80000
0)
#80500
b111001100011000 $
b111001100011000 5
b110011100110110000110111011000 7
b111001011001001 '
b111001011001001 3
b1000110 ,
b1000110 1
b1000110 -
b1000100000011010011011010111001 6
b10000011100100010100011100001 &
b10000011100100010100011100001 4
b10000011100100010100011100001 8
1)
#81000
0)
#81500
b1000101010100011 '
b1000101010100011 3
b11110000100011111011001100100111 7
b10000110101101 $
b10000110101101 5
b110100100111001110100111100000 6
b1000100000011010011011010111001 &
b1000100000011010011011010111001 4
b1000100000011010011011010111001 8
b1000111 -
b1000111 1
b1000111 ,
1)
#82000
0)
#82500
b111011001011010 $
b111011001011010 5
b111001111100101010000011110000 7
b111110101011000 '
b111110101011000 3
b1001000 ,
b1001000 1
b1001000 -
b1101110100011111000101011010000 6
b110100100111001110100111100000 &
b110100100111001110100111100000 4
b110100100111001110100111100000 8
1)
#83000
0)
