exp_6_DLP_design/src/serial_pe/serial_pe.v
module serial_pe(
  input                clk,
  input                rst_n,
  input  signed [15:0] neuron,
  input  signed [15:0] weight,
  input         [ 1:0] ctl,
  input                vld_i,
  output        [31:0] result,
  output reg           vld_o
);

/*乘法器*/  /*TODO*/
wire signed [31:0] mult_res = neuron * weight;
reg [31:0] psum_r;

/*加法器*/  /*TODO*/
wire [31:0] psum_d = psum_r + mult_res;

/*部分和寄存器*/
always@(posedge clk or negedge rst_n)
if(!rst_n) begin
  psum_r <= 32'h0;
end else if(vld_i) begin
  psum_r <= psum_d;
end
else begin
  psum_r <= 32'h0;
end

always@(posedge clk or negedge rst_n)
if(!rst_n) begin
  vld_o <= 1'b0;
end else if(ctl[1]) begin
  vld_o <= 1'b1;
end else begin
  vld_o <= 1'b0;
end

assign result = psum_r;

endmodule

exp_6_DLP_design/src/serial_pe/tb_top_0.v
`timescale 1ns/1ps

module tb_top;
localparam WIDTH = 32;

reg        clk; // clk
reg        rst_n; // reset

initial begin
    clk = 1'b0;
    forever #0.5 clk = ~clk;
end
initial begin
    rst_n = 1'b0;
    #10 rst_n = 1'b1;
end
initial begin
  $dumpfile("tb_top_0.vcd");
  $dumpvars(0, tb_top);
end
initial begin
    #10000;
    $finish;
end

reg [7  :0] inst[3:0];
reg [511:0] neuron[139:0];
reg [511:0] weight[139:0];
reg [ 44:0] result[3:0];

initial
begin
  $readmemh("/Users/yulong/Documents/intelligent-computing-systems-library/exp_6_DLP_design/data/inst", inst);
  $readmemh("/Users/yulong/Documents/intelligent-computing-systems-library/exp_6_DLP_design/data/neuron", neuron);
  $readmemh("/Users/yulong/Documents/intelligent-computing-systems-library/exp_6_DLP_design/data/weight", weight);
  $readmemb("/Users/yulong/Documents/intelligent-computing-systems-library/exp_6_DLP_design/data/result", result);
end

reg [ 1:0]   inst_addr;
reg [12:0]   iter;
reg [15:0]   neuron_addr;
reg [15:0]   weight_addr;

wire [  7:0] pe_inst        = inst[inst_addr];
wire [511:0] pe_weight_line = weight[weight_addr[15:5]];
wire [511:0] pe_neuron_line = neuron[neuron_addr[15:5]];
wire [ 15:0] pe_weight      = pe_weight_line[(16*(31-weight_addr[4:0]))+:16];
wire [ 15:0] pe_neuron      = pe_neuron_line[(16*(31-neuron_addr[4:0]))+:16];
wire [1:0] pe_ctl;
assign pe_ctl[0] = (iter[12:0] == 13'h0);
assign pe_ctl[1] = (iter[12:5] == (pe_inst[7:0] - 1'b1)) && (iter[4:0] == 5'h1f);

reg pe_vld_i;
always@(posedge clk or negedge rst_n) begin
  if(!rst_n) begin
    pe_vld_i <= 1'b0;
  end else if((inst_addr == 2'h0) && (neuron_addr == 16'h0) && (weight_addr == 16'h0)) begin
    pe_vld_i <= 1'b1;
  end else if(pe_ctl[1] && pe_vld_i && (inst_addr != 2'h3)) begin
    pe_vld_i <= 1'b0;
  end else begin
    pe_vld_i <= 1'b1;
  end
end

always@(posedge clk or negedge rst_n) begin
  if(!rst_n) begin
    iter <= 13'b0;
  end else if(pe_ctl[1] && pe_vld_i && (inst_addr != 2'h3)) begin
    iter <= 13'b0;
  end else if(pe_vld_i) begin
    iter <= iter + 1'b1;
  end
end

always@(posedge clk or negedge rst_n) begin
  if(!rst_n) begin
    inst_addr <= 2'b0;
  end else if(pe_ctl[1] && pe_vld_i && (inst_addr != 2'h3)) begin
    inst_addr <= inst_addr + 1'b1;
  end
end

always@(posedge clk or negedge rst_n) begin
  if(!rst_n) begin
    weight_addr <= 16'h0;
  end else if(pe_vld_i) begin
    weight_addr <= weight_addr + 1'b1;
  end
end

always@(posedge clk or negedge rst_n) begin
  if(!rst_n) begin
    neuron_addr <= 16'h0;
  end else if(pe_vld_i) begin
    neuron_addr <= neuron_addr + 1'b1;
  end
end

wire [31:0] pe_result;
wire pe_vld_o;
serial_pe u_serial_pe (
  .clk                  (clk      ),
  .rst_n                (rst_n    ),
  .neuron               (pe_neuron),
  .weight               (pe_weight),
  .ctl                  (pe_ctl   ),
  .vld_i                (pe_vld_i ),
  .result               (pe_result),
  .vld_o                (pe_vld_o )
);

reg [1:0] result_addr;
reg compare_pass;
always@(posedge clk or negedge rst_n) begin
  if(!rst_n) begin
    result_addr <= 2'h0;
  end else if(pe_vld_o) begin
    result_addr <= result_addr + 1'b1;
  end
end

always@(posedge clk or negedge rst_n) begin
 if(!rst_n) begin
   compare_pass <= 1'b1;
 end else if(pe_vld_o && (pe_result != result[result_addr][31:0])) begin
   $display("FAIL:\n num.%d result not correct!!!\npe_result is %x,result is %x\n", result_addr,pe_result,result[result_addr][31:0]);
  //  $display("FAIL: num.%d result not correct!!!", result_addr);
   compare_pass <= 1'b0;
 end else if(pe_vld_o && (pe_result == result[result_addr][31:0])) begin
   $display("INFO: num.%d result is correct.", result_addr);
 end
end

endmodule

exp_6_DLP_design/src/serial_pe/tb_top_0.vcd
$date
	Tue Apr 25 09:39:22 2023
$end
$version
	Icarus Verilog
$end
$timescale
	1ps
$end
$scope module tb_top $end
$var wire 8 ! pe_inst [7:0] $end
$var wire 512 " pe_neuron_line [511:0] $end
$var wire 512 # pe_weight_line [511:0] $end
$var wire 16 $ pe_weight [15:0] $end
$var wire 1 % pe_vld_o $end
$var wire 32 & pe_result [31:0] $end
$var wire 16 ' pe_neuron [15:0] $end
$var wire 2 ( pe_ctl [1:0] $end
$var reg 1 ) clk $end
$var reg 1 * compare_pass $end
$var reg 2 + inst_addr [1:0] $end
$var reg 13 , iter [12:0] $end
$var reg 16 - neuron_addr [15:0] $end
$var reg 1 . pe_vld_i $end
$var reg 2 / result_addr [1:0] $end
$var reg 1 0 rst_n $end
$var reg 16 1 weight_addr [15:0] $end
$scope module u_serial_pe $end
$var wire 1 ) clk $end
$var wire 2 2 ctl [1:0] $end
$var wire 16 3 neuron [15:0] $end
$var wire 32 4 result [31:0] $end
$var wire 1 0 rst_n $end
$var wire 1 . vld_i $end
$var wire 16 5 weight [15:0] $end
$var wire 32 6 psum_d [31:0] $end
$var wire 32 7 mult_res [31:0] $end
$var reg 32 8 psum_r [31:0] $end
$var reg 1 % vld_o $end
$upscope $end
$upscope $end
$enddefinitions $end
#0
$dumpvars
b0 8
bx 7
bx 6
bx 5
b0 4
bx 3
bx 2
bx 1
00
bx /
x.
bx -
bx ,
bx +
x*
0)
bx (
bx '
b0 &
0%
bx $
bx #
bx "
bx !
$end
#500
b11100001010011010100101001111000 6
b11100001010011010100101001111000 7
b101110111111100 $
b101110111111100 5
b1011101111111000110101110000110011011001010101000111010110101101111000000101110000001101100101011111111011001010010110011100110110111101101001111100111011011110111001001100010011000100110110100000111100000010001001101111011011101111010100000111011001100110010001100010010001100000110001000100010101010000010110110111101101111010001001111010101011001110010100111000011111100110101000011111110110111100000011010000011000110010110100110011100010110010110100101110000100001100010001000110001110000110110101101101000 #
b1010110001100010 '
b1010110001100010 3
b10101100011000101000110111100101001100110010100001111111011101110110100101110000000010100110011010111010010101100100110111000100000000111011100011100010100100011110011101010100010111111100011010010100001110010000111001101111001111100010101011011111110001001010011010101010110010001101000110000111101110000001111001110110111001010110111001110010110100010101111011000101101101001111111010101101001110100111000010110110110101110110100000011011000111111101110110101101010100111000000101111000101010100101001011111111 "
0.
b1 (
b1 2
b0 ,
b10100 !
b0 +
b0 1
b0 -
b0 /
1*
1)
#1000
0)
#1500
1)
#2000
0)
#2500
1)
#3000
0)
#3500
1)
#4000
0)
#4500
1)
#5000
0)
#5500
1)
#6000
0)
#6500
1)
#7000
0)
#7500
1)
#8000
0)
#8500
1)
#9000
0)
#9500
1)
#10000
0)
10
#10500
1.
1)
#11000
0)
#11500
b1000110111100101 '
b1000110111100101 3
b11010000000100101111110011011110 7
b110101110000110 $
b110101110000110 5
b10110001011000000100011101010110 6
b11100001010011010100101001111000 &
b11100001010011010100101001111000 4
b11100001010011010100101001111000 8
b1 -
b1 1
b0 (
b0 2
b1 ,
1)
#12000
0)
#12500
b110110010101010 $
b110110010101010 5
b10101101101101101100010010000 7
b11001100101000 '
b11001100101000 3
b10 ,
b10 1
b10 -
b11000111000101110001111111100110 6
b10110001011000000100011101010110 &
b10110001011000000100011101010110 4
b10110001011000000100011101010110 8
1)
#13000
0)
#13500
b111111101110111 '
b111111101110111 3
b11101010010111000001101111010 7
b11101011010110 $
b11101011010110 5
b11100100011000101010001101100000 6
b11000111000101110001111111100110 &
b11000111000101110001111111100110 4
b11000111000101110001111111100110 8
b11 -
b11 1
b11 ,
1)
#14000
0)
#14500
b1111000000101110 $
b1111000000101110 5
b11111001011110111111001000100000 7
b110100101110000 '
b110100101110000 3
b100 ,
b100 1
b100 -
b11011101110111101001010110000000 6
b11100100011000101010001101100000 &
b11100100011000101010001101100000 4
b11100100011000101010001101100000 8
1)
#15000
0)
#15500
b101001100110 '
b101001100110 3
b10001101001100001111100 7
b11011001010 $
b11011001010 5
b11011110001001010010110111111100 6
b11011101110111101001010110000000 &
b11011101110111101001010110000000 4
b11011101110111101001010110000000 8
b101 -
b101 1
b101 ,
1)
#16000
0)
#16500
b1111111101100101 $
b1111111101100101 5
b1010100010110111101110 7
b1011101001010110 '
b1011101001010110 3
b110 ,
b110 1
b110 -
b11011110010011110101101111101010 6
b11011110001001010010110111111100 &
b11011110001001010010110111111100 4
b11011110001001010010110111111100 8
1)
#17000
0)
#17500
b100110111000100 '
b100110111000100 3
b1101101000111000111000011000 7
b10110011100110 $
b10110011100110 5
b11101011111100101110101000000010 6
b11011110010011110101101111101010 &
b11011110010011110101101111101010 4
b11011110010011110101101111101010 8
b111 -
b111 1
b111 ,
1)
#18000
0)
#18500
b1101111011010011 $
b1101111011010011 5
b11111111100001001010000010101000 7
b1110111000 '
b1110111000 3
b1000 ,
b1000 1
b1000 -
b11101011011101111000101010101010 6
b11101011111100101110101000000010 &
b11101011111100101110101000000010 4
b11101011111100101110101000000010 8
1)
#19000
0)
#19500
b1110001010010001 '
b1110001010010001 3
b10110100110001001111011111 7
b1110011101101111 $
b1110011101101111 5
b11101110010010101001111010001001 6
b11101011011101111000101010101010 &
b11101011011101111000101010101010 4
b11101011011101111000101010101010 8
b1001 -
b1001 1
b1001 ,
1)
#20000
0)
#20500
b111001001100010 $
b111001001100010 5
b11110100111110011111011000101000 7
b1110011101010100 '
b1110011101010100 3
b1010 ,
b1010 1
b1010 -
b11100011010001001001010010110001 6
b11101110010010101001111010001001 &
b11101110010010101001111010001001 4
b11101110010010101001111010001001 8
1)
#21000
0)
#21500
b101111111000110 '
b101111111000110 3
b100100110100101001001101001110 7
b110001001101101 $
b110001001101101 5
b1000000101110010011111111111 6
b11100011010001001001010010110001 &
b11100011010001001001010010110001 4
b11100011010001001001010010110001 8
b1011 -
b1011 1
b1011 ,
1)
#22000
0)
#22500
b11110000001 $
b11110000001 5
b11111100110101110011111110111001 7
b1001010000111001 '
b1001010000111001 3
b1100 ,
b1100 1
b1100 -
b100111011100110011110111000 6
b1000000101110010011111111111 &
b1000000101110010011111111111 4
b1000000101110010011111111111 8
1)
#23000
0)
#23500
b111001101111 '
b111001101111 3
b1000110010010110001010101 7
b1001101111011 $
b1001101111011 5
b110000001111001010000001101 6
b100111011100110011110111000 &
b100111011100110011110111000 4
b100111011100110011110111000 8
b1101 -
b1101 1
b1101 ,
1)
#24000
0)
#24500
b111011110101000 $
b111011110101000 5
b11101000011100101000110010000 7
b11111000101010 '
b11111000101010 3
b1110 ,
b1110 1
b1110 -
b100011000101011110010110011101 6
b110000001111001010000001101 &
b110000001111001010000001101 4
b110000001111001010000001101 8
1)
#25000
0)
#25500
b1101111111000100 '
b1101111111000100 3
b11111000100010111100000000001100 7
b11101100110011 $
b11101100110011 5
b11011101000011010010110101001 6
b100011000101011110010110011101 &
b100011000101011110010110011101 4
b100011000101011110010110011101 8
b1111 -
b1111 1
b1111 ,
1)
#26000
0)
#26500
b10001100010010 $
b10001100010010 5
b11110011110000101111010111110100 7
b1010011010101010 '
b1010011010101010 3
b10000 ,
b10000 1
b10000 -
b1111011001001001101110011101 6
b11011101000011010010110101001 &
b11011101000011010010110101001 4
b11011101000011010010110101001 8
1)
#27000
0)
#27500
b1100100011010001 '
b1100100011010001 3
b11110101100100100001000000000010 7
b11000001100010 $
b11000001100010 5
b100111101101010101110011111 6
b1111011001001001101110011101 &
b1111011001001001101110011101 4
b1111011001001001101110011101 8
b10001 -
b10001 1
b10001 ,
1)
#28000
0)
#28500
b10001010101000 $
b10001010101000 5
b11101111101101111000000011000000 7
b1000011110111000 '
b1000011110111000 3
b10010 ,
b10010 1
b10010 -
b11110100101011100010110001011111 6
b100111101101010101110011111 &
b100111101101010101110011111 4
b100111101101010101110011111 8
1)
#29000
0)
#29500
b1111001110110 '
b1111001110110 3
b101011100010011101100011110 7
b10110110111101 $
b10110110111101 5
b11111010000111110110011101111101 6
b11110100101011100010110001011111 &
b11110100101011100010110001011111 4
b11110100101011100010110001011111 8
b10011 -
b10011 1
b10011 ,
1)
#30000
0)
#30500
b1011110100010011 $
b1011110100010011 5
b110111100100011110100101010 7
b1110010101101110 '
b1110010101101110 3
b10100 ,
b10100 1
b10100 -
b1000100011010010010100111 6
b11111010000111110110011101111101 &
b11111010000111110110011101111101 4
b11111010000111110110011101111101 8
1)
#31000
0)
#31500
b111001011010001 '
b111001011010001 3
b11101100111001010001011100010111 7
b1101010101100111 $
b1101010101100111 5
b11101101111101101011101110111110 6
b1000100011010010010100111 &
b1000100011010010010100111 4
b1000100011010010010100111 8
b10101 -
b10101 1
b10101 ,
1)
#32000
0)
#32500
b10100111000011 $
b10100111000011 5
b1111011101011011110100001111 7
b101111011000101 '
b101111011000101 3
b10110 ,
b10110 1
b10110 -
b11111101011011000111100011001101 6
b11101101111101101011101110111110 &
b11101101111101101011101110111110 4
b11101101111101101011101110111110 8
1)
#33000
0)
#33500
b1011010011111110 '
b1011010011111110 3
b11101101111010100101100000 7
b1111001101010000 $
b1111001101010000 5
b1001001000010001000101101 6
b11111101011011000111100011001101 &
b11111101011011000111100011001101 4
b11111101011011000111100011001101 8
b10111 -
b10111 1
b10111 ,
1)
#34000
0)
#34500
b1111111011011110 $
b1111111011011110 5
b10111011100010001001100 7
b1010110100111010 '
b1010110100111010 3
b11000 ,
b11000 1
b11000 -
b1100000011110011001111001 6
b1001001000010001000101101 &
b1001001000010001000101101 4
b1001001000010001000101101 8
1)
#35000
0)
#35500
b111000010110110 '
b111000010110110 3
b10110111011111000100100010 7
b11010000011 $
b11010000011 5
b100010111111101011110011011 6
b1100000011110011001111001 &
b1100000011110011001111001 4
b1100000011110011001111001 8
b11001 -
b11001 1
b11001 ,
1)
#36000
0)
#36500
b1100101101001 $
b1100101101001 5
b11111011111110001000000110101000 7
b1101011101101000 '
b1101011101101000 3
b11010 ,
b11010 1
b11010 -
b10110000101100101000011 6
b100010111111101011110011011 &
b100010111111101011110011011 4
b100010111111101011110011011 8
1)
#37000
0)
#37500
b1101100011111 '
b1101100011111 3
b11110101011100010101000111000111 7
b1001110001011001 $
b1001110001011001 5
b11110101110010011010101100001010 6
b10110000101100101000011 &
b10110000101100101000011 4
b10110000101100101000011 8
b11011 -
b11011 1
b11011 ,
1)
#38000
0)
#38500
b110100101110000 $
b110100101110000 5
b11110001110111001111000010110000 7
b1101110110101101 '
b1101110110101101 3
b11100 ,
b11100 1
b11100 -
b11100111101001101001101110111010 6
b11110101110010011010101100001010 &
b11110101110010011010101100001010 4
b11110101110010011010101100001010 8
1)
#39000
0)
#39500
b101001110000001 '
b101001110000001 3
b11011000001111111001110100100010 7
b1000011000100010 $
b1000011000100010 5
b10111111111001100011100011011100 6
b11100111101001101001101110111010 &
b11100111101001101001101110111010 4
b11100111101001101001101110111010 8
b11101 -
b11101 1
b11101 ,
1)
#40000
0)
#40500
b11000111000011 $
b11000111000011 5
b10111011101000111001101111110 7
b111100010101010 '
b111100010101010 3
b11110 ,
b11110 1
b11110 -
b11010111010110101010110001011010 6
b10111111111001100011100011011100 &
b10111111111001100011100011011100 4
b10111111111001100011100011011100 8
1)
#41000
0)
#41500
b101001011111111 '
b101001011111111 3
b100010110100100100110010011000 7
b110101101101000 $
b110101101101000 5
b11111010001011001111100011110010 6
b11010111010110101010110001011010 &
b11010111010110101010110001011010 4
b11010111010110101010110001011010 8
b11111 -
b11111 1
b11111 ,
1)
#42000
0)
#42500
b11000011010001101001010000001011100100110110010110101001111010000010010111101100101101111100110011010011100110011101011110100011100100010111000111100001110111101101101101100111110111001111100010101001011010100000111011001110000010101010110000111010001011101001000110011010010100000001101000001010000010101111010110111110000011001110100100101001101011011000110100001010110011000100101100100100111101010010000110000110111110000001000101101001111110100011011101100010110111001011000101100110110011011110101000001011 #
b1100001101000110 $
b1100001101000110 5
b1110110100010100011000101111001100110101010010011001000111100000100111001010001110110111010101000100010010101000110101100101100010100110000110111111011011011000010011111100010000110111100011000011101111111100110111010011001001011111010000100011100111100110100110110010001010010110000110110100111001110000101101011010111010101100010000100110000010100101010101101001011010100000111000010011111001110011011000101001011001111101001010111110010101101010000111010111101110011100110111101101110100100111001100011110110 "
b11100011111000011000011110111100 7
b111011010001010 '
b111011010001010 3
b100000 ,
b100000 1
b100000 -
b11011110000011101000000010101110 6
b11111010001011001111100011110010 &
b11111010001011001111100011110010 4
b11111010001011001111100011110010 8
1)
#43000
0)
#43500
b11000101111001 '
b11000101111001 3
b11101011001000110001010000110011 7
b1001010000001011 $
b1001010000001011 5
b11001001001100011001010011100001 6
b11011110000011101000000010101110 &
b11011110000011101000000010101110 4
b11011110000011101000000010101110 8
b100001 -
b100001 1
b100001 ,
1)
#44000
0)
#44500
b1001001101100101 $
b1001001101100101 5
b101011000000000010111010110100 7
b1001101010100100 '
b1001101010100100 3
b100010 ,
b100010 1
b100010 -
b11110100001100011100001110010101 6
b11001001001100011001010011100001 &
b11001001001100011001010011100001 4
b11001001001100011001010011100001 8
1)
#45000
0)
#45500
b1100100011110000 '
b1100100011110000 3
b10010100001001000100110000000 7
b1010100111101000 $
b1010100111101000 5
b110101101100100110100010101 6
b11110100001100011100001110010101 &
b11110100001100011100001110010101 4
b11110100001100011100001110010101 8
b100011 -
b100011 1
b100011 ,
1)
#46000
0)
#46500
b10010111101100 $
b10010111101100 5
b1011100110011110011110101100 7
b100111001010001 '
b100111001010001 3
b100100 ,
b100100 1
b100100 -
b10010010100000011010011000001 6
b110101101100100110100010101 &
b110101101100100110100010101 4
b110101101100100110100010101 8
1)
#47000
0)
#47500
b1101101110101010 '
b1101101110101010 3
b1010001111111001000101111000 7
b1011011111001100 $
b1011011111001100 5
b11100100011111100011000111001 6
b10010010100000011010011000001 &
b10010010100000011010011000001 4
b10010010100000011010011000001 8
b100101 -
b100101 1
b100101 ,
1)
#48000
0)
#48500
b1101001110011001 $
b1101001110011001 5
b11111010000010111100000000110100 7
b10001001010100 '
b10001001010100 3
b100110 ,
b100110 1
b100110 -
b10110100110111000011001101101 6
b11100100011111100011000111001 &
b11100100011111100011000111001 4
b11100100011111100011000111001 8
1)
#49000
0)
#49500
b110101100101100 '
b110101100101100 3
b11101111000110100011000100000100 7
b1101011110100011 $
b1101011110100011 5
b101101101011011011101110001 6
b10110100110111000011001101101 &
b10110100110111000011001101101 4
b10110100110111000011001101101 8
b100111 -
b100111 1
b100111 ,
1)
#50000
0)
#50500
b1001000101110001 $
b1001000101110001 5
b11011100001000100000010110111101 7
b101001100001101 '
b101001100001101 3
b101000 ,
b101000 1
b101000 -
b11100001110101111011110100101110 6
b101101101011011011101110001 &
b101101101011011011101110001 4
b101101101011011011101110001 8
1)
#51000
0)
#51500
b1111101101101100 '
b1111101101101100 3
b100010011111001110101000 7
b1110000111011110 $
b1110000111011110 5
b11100010011000011011000011010110 6
b11100001110101111011110100101110 &
b11100001110101111011110100101110 4
b11100001110101111011110100101110 8
b101001 -
b101001 1
b101001 ,
1)
#52000
0)
#52500
b1101101101100111 $
b1101101101100111 5
b11111010010011000110000111101110 7
b10011111100010 '
b10011111100010 3
b101010 ,
b101010 1
b101010 -
b11011100101011100001001011000100 6
b11100010011000011011000011010110 &
b11100010011000011011000011010110 4
b11100010011000011011000011010110 8
1)
#53000
0)
#53500
b1101111000110 '
b1101111000110 3
b11111100001100110000111111010000 7
b1101110011111000 $
b1101110011111000 5
b11011000111000010010001010010100 6
b11011100101011100001001011000100 &
b11011100101011100001001011000100 4
b11011100101011100001001011000100 8
b101011 -
b101011 1
b101011 ,
1)
#54000
0)
#54500
b1010100101101010 $
b1010100101101010 5
b11110101110110110001100100101100 7
b1110111111110 '
b1110111111110 3
b101100 ,
b101100 1
b101100 -
b11001110101111000011101111000000 6
b11011000111000010010001010010100 &
b11011000111000010010001010010100 4
b11011000111000010010001010010100 8
1)
#55000
0)
#55500
b110111010011001 '
b110111010011001 3
b110011001010101110100011110 7
b111011001110 $
b111011001110 5
b11010101001000011001100011011110 6
b11001110101111000011101111000000 &
b11001110101111000011101111000000 4
b11001110101111000011101111000000 8
b101101 -
b101101 1
b101101 ,
1)
#56000
0)
#56500
b101010101100 $
b101010101100 5
b1111111000100101000101100 7
b10111110100001 '
b10111110100001 3
b101110 ,
b101110 1
b101110 -
b11010111000111011110001100001010 6
b11010101001000011001100011011110 &
b11010101001000011001100011011110 4
b11010101001000011001100011011110 8
1)
#57000
0)
#57500
b1110011110011 '
b1110011110011 3
b110100101000100000110101010 7
b11101000101110 $
b11101000101110 5
b11011101101100100010010010110100 6
b11010111000111011110001100001010 &
b11010111000111011110001100001010 4
b11010111000111011110001100001010 8
b101111 -
b101111 1
b101111 ,
1)
#58000
0)
#58500
b1001000110011010 $
b1001000110011010 5
b11011110100011001100101000111010 7
b100110110010001 '
b100110110010001 3
b110000 ,
b110000 1
b110000 -
b10111100001111101110111011101110 6
b11011101101100100010010010110100 &
b11011101101100100010010010110100 4
b11011101101100100010010010110100 8
1)
#59000
0)
#59500
b100101100001101 '
b100101100001101 3
b10111011110111010111101010010 7
b101000000011010 $
b101000000011010 5
b11010011101110101001111001000000 6
b10111100001111101110111011101110 &
b10111100001111101110111011101110 4
b10111100001111101110111011101110 8
b110001 -
b110001 1
b110001 ,
1)
#60000
0)
#60500
b101000001010 $
b101000001010 5
b11111100100001001011100000110000 7
b1010011100111000 '
b1010011100111000 3
b110010 ,
b110010 1
b110010 -
b11010000001111110101011001110000 6
b11010011101110101001111001000000 &
b11010011101110101001111001000000 4
b11010011101110101001111001000000 8
1)
#61000
0)
#61500
b101101011010111 '
b101101011010111 3
b11111100010111000010111010010010 7
b1111010110111110 $
b1111010110111110 5
b11001100100110111000010100000010 6
b11010000001111110101011001110000 &
b11010000001111110101011001110000 4
b11010000001111110101011001110000 8
b110011 -
b110011 1
b110011 ,
1)
#62000
0)
#62500
b110011101001 $
b110011101001 5
b100010101111111000000001001 7
b101011000100001 '
b101011000100001 3
b110100 ,
b110100 1
b110100 -
b11010000111100110111010100001011 6
b11001100100110111000010100000010 &
b11001100100110111000010100000010 4
b11001100100110111000010100000010 8
1)
#63000
0)
#63500
b11000001010010 '
b11000001010010 3
b111110111011100100101101010 7
b10100110101101 $
b10100110101101 5
b11011000110100010011111001110101 6
b11010000111100110111010100001011 &
b11010000111100110111010100001011 4
b11010000111100110111010100001011 8
b110101 -
b110101 1
b110101 ,
1)
#64000
0)
#64500
b1000110100001010 $
b1000110100001010 5
b100110000010011111111111101110 7
b1010101101001011 '
b1010101101001011 3
b110110 ,
b110110 1
b110110 -
b11111110110110110011111001100011 6
b11011000110100010011111001110101 &
b11011000110100010011111001110101 4
b11011000110100010011111001110101 8
1)
#65000
0)
#65500
b101000001110000 '
b101000001110000 3
b11101111110000001101000011010000 7
b1100110001001011 $
b1100110001001011 5
b11101110100111000000111100110011 6
b11111110110110110011111001100011 &
b11111110110110110011111001100011 4
b11111110110110110011111001100011 8
b110111 -
b110111 1
b110111 ,
1)
#66000
0)
#66500
b10010011110101 $
b10010011110101 5
b11110010000001110110010110001101 7
b1001111100111001 '
b1001111100111001 3
b111000 ,
b111000 1
b111000 -
b11100000101000110111010011000000 6
b11101110100111000000111100110011 &
b11101110100111000000111100110011 4
b11101110100111000000111100110011 8
1)
#67000
0)
#67500
b1011000101001011 '
b1011000101001011 3
b11110101101100010111100001000010 7
b10000110000110 $
b10000110000110 5
b11010110010101001110110100000010 6
b11100000101000110111010011000000 &
b11100000101000110111010011000000 4
b11100000101000110111010011000000 8
b111001 -
b111001 1
b111001 ,
1)
#68000
0)
#68500
b1111100000010001 $
b1111100000010001 5
b11111110000011110111111111100101 7
b11111010010101 '
b11111010010101 3
b111010 ,
b111010 1
b111010 -
b11010100011001000110110011100111 6
b11010110010101001110110100000010 &
b11010110010101001110110100000010 4
b11010110010101001110110100000010 8
1)
#69000
0)
#69500
b1111001010110101 '
b1111001010110101 3
b11111010011111110100000111000010 7
b110100111111010 $
b110100111111010 5
b11001110111000111010111010101001 6
b11010100011001000110110011100111 &
b11010100011001000110110011100111 4
b11010100011001000110110011100111 8
b111011 -
b111011 1
b111011 ,
1)
#70000
0)
#70500
b11011101100010 $
b11011101100010 5
b11001100000011111101011010 7
b111010111101 '
b111010111101 3
b111100 ,
b111100 1
b111100 -
b11010010000100111110111000000011 6
b11001110111000111010111010101001 &
b11001110111000111010111010101001 4
b11001110111000111010111010101001 8
1)
#71000
0)
#71500
b1100111001101111 '
b1100111001101111 3
b110110101100001111010111111 7
b1101110010110001 $
b1101110010110001 5
b11011000111010100000110011000010 6
b11010010000100111110111000000011 &
b11010010000100111110111000000011 4
b11010010000100111110111000000011 8
b111101 -
b111101 1
b111101 ,
1)
#72000
0)
#72500
b110011011001101 $
b110011011001101 5
b101100011001110001110110110111 7
b110111010010011 '
b110111010010011 3
b111110 ,
b111110 1
b111110 -
b101010100010010101001111001 6
b11011000111010100000110011000010 &
b11011000111010100000110011000010 4
b11011000111010100000110011000010 8
1)
#73000
0)
#73500
b1001100011110110 '
b1001100011110110 3
b1000110101100110111010010010 7
b1110101000001011 $
b1110101000001011 5
b1110001001111001100100001011 6
b101010100010010101001111001 &
b101010100010010101001111001 4
b101010100010010101001111001 8
b111111 -
b111111 1
b111111 ,
1)
#74000
0)
#74500
b11010001011110011111101100111111011001101001110110001100111100001000111000110000000010000001011100010111001101111001111000100010100111010110101110011010110001100011011101001100011111110111011010110100000010011010001100011010011000000100010111111000101111010110010010111101110111001110111101001000011000101001001000010110110111001001000010110010001111001110111100011011101101100110001011100001110001011000001010100110011001101010101100100110101011100110011111001110110011101000101011000000000101011110001000111001 #
b1101000101111001 $
b1101000101111001 5
b10111101101010111101001110100101101010001101101001000110000000100001011110101010010011010001010000000101011001100000101101110101110110101001011001100010100001011011110100100000111110010110100100100111110000110001101001011101000100000110011110011111000100011100101100101110101111100010010110011010101010011100001101110000110001100010000111000011000011111000010101011101101111101100101101011110101010000101011110010110001100101011010101100000001110110101011101000100111111011101101001010111110110000000011001110000 "
b1100000011100100000011010011 7
b1011110110101011 '
b1011110110101011 3
b1000000 ,
b1000000 1
b1000000 -
b11010001101011101100111011110 6
b1110001001111001100100001011 &
b1110001001111001100100001011 4
b1110001001111001100100001011 8
1)
#75000
0)
#75500
b1101001110100101 '
b1101001110100101 3
b110100101101110010011011 7
b1111101100111111 $
b1111101100111111 5
b11011000010001011011001111001 6
b11010001101011101100111011110 &
b11010001101011101100111011110 4
b11010001101011101100111011110 8
b1000001 -
b1000001 1
b1000001 ,
1)
#76000
0)
#76500
b110011010011101 $
b110011010011101 5
b11011101000100010110100110110010 7
b1010100011011010 '
b1010100011011010 3
b1000010 ,
b1000010 1
b1000010 -
b11111000000110100010000000101011 6
b11011000010001011011001111001 &
b11011000010001011011001111001 4
b11011000010001011011001111001 8
1)
#77000
0)
#77500
b100011000000010 '
b100011000000010 3
b11100000100010001011100111100000 7
b1000110011110000 $
b1000110011110000 5
b11011000101000101101101000001011 6
b11111000000110100010000000101011 &
b11111000000110100010000000101011 4
b11111000000110100010000000101011 8
b1000011 -
b1000011 1
b1000011 ,
1)
#78000
0)
#78500
b1000111000110000 $
b1000111000110000 5
b11110101011110101011101111100000 7
b1011110101010 '
b1011110101010 3
b1000100 ,
b1000100 1
b1000100 -
b11001110000111011001010111101011 6
b11011000101000101101101000001011 &
b11011000101000101101101000001011 4
b11011000101000101101101000001011 8
1)
#79000
0)
#79500
b100110100010100 '
b100110100010100 3
b10011011111000110011001100 7
b100000010111 $
b100000010111 5
b11010000100011010010001010110111 6
b11001110000111011001010111101011 &
b11001110000111011001010111101011 4
b11001110000111011001010111101011 8
b1000101 -
b1000101 1
b1000101 ,
1)
#80000
0)
#80500
b1011100110111 $
b1011100110111 5
b11111010101001011101010 7
b10101100110 '
b10101100110 3
b1000110 ,
b1000110 1
b1000110 -
b11010001000010100111010110100001 6
b11010000100011010010001010110111 &
b11010000100011010010001010110111 4
b11010000100011010010001010110111 8
1)
#81000
0)
#81500
b101101110101 '
b101101110101 3
b11111011100111101011101110001010 7
b1001111000100010 $
b1001111000100010 5
b11001100101010010011000100101011 6
b11010001000010100111010110100001 &
b11010001000010100111010110100001 4
b11010001000010100111010110100001 8
b1000111 -
b1000111 1
b1000111 ,
1)
#82000
0)
#82500
b1001110101101011 $
b1001110101101011 5
b1110011010000101101010110010 7
b1101101010010110 '
b1101101010010110 3
b1001000 ,
b1001000 1
b1001000 -
b11011011000100011000101111011101 6
b11001100101010010011000100101011 &
b11001100101010010011000100101011 4
b11001100101010010011000100101011 8
1)
#83000
0)
#83500
b110001010000101 '
b110001010000101 3
b11011001000010110011010011011110 7
b1001101011000110 $
b1001101011000110 5
b10110100000111001100000010111011 6
b11011011000100011000101111011101 &
b11011011000100011000101111011101 4
b11011011000100011000101111011101 8
b1001001 -
b1001001 1
b1001001 ,
1)
#84000
0)
